{
  "consumeCatalyst": false,
  "location": "interaction:arcane_crafter",
  "traits": {},
  "allowRotate": true,
  "showInJei": true,
  "baseRenderer": {
    "state": {
      "id": "arcanearchives:storage_shaped_quartz",
      "meta": 0
    },
    "type": "blockstate"
  },
  "isOpaqueCube": true,
  "basePattern": {
    "structureDir": [
      "LEFT",
      "UP",
      "BACK"
    ],
    "pattern": [
      [
        "@AA",
        "BCD"
      ],
      [
        "AAA",
        "ECD"
      ]
    ],
    "aisleRepetitions": [
      [
        1,
        1
      ],
      [
        1,
        1
      ]
    ],
    "predicates": {
      "A": {
        "states": [
          {
            "id": "arcanearchives:storage_shaped_quartz",
            "meta": 0
          }
        ],
        "type": "states"
      },
      "controller": {
        "location": "interaction:arcane_crafter",
        "type": "component"
      },
      "B": {
        "states": [
          {
            "id": "arcanearchives:radiant_chest",
            "meta": 0
          }
        ],
        "type": "states"
      },
      "C": {
        "states": [
          {
            "id": "arcanearchives:gemcutters_table",
            "meta": 4
          }
        ],
        "type": "states"
      },
      "D": {
        "states": [
          {
            "id": "arcanearchives:gemcutters_table",
            "meta": 5
          }
        ],
        "type": "states"
      },
      "E": {
        "states": [
          {
            "id": "arcanearchives:radiant_tank",
            "meta": 0
          }
        ],
        "type": "states"
      },
      "air": {
        "type": "air"
      },
      "any": {
        "type": "any"
      }
    },
    "symbolMap": {
      "@": [
        "controller"
      ],
      " ": [
        "any"
      ],
      "A": [
        "A"
      ],
      "B": [
        "B"
      ],
      "C": [
        "C"
      ],
      "D": [
        "D"
      ],
      "E": [
        "E"
      ],
      "-": [
        "air"
      ]
    }
  },
  "recipeMap": "arcane"
}